luxconnector/__init__.py
luxconnector/listener.py
luxconnector/lux_device.py
luxconnector/main.py
luxconnector/LuxServer/Azure.Core.dll
luxconnector/LuxServer/Azure.Storage.Blobs.dll
luxconnector/LuxServer/Azure.Storage.Common.dll
luxconnector/LuxServer/Camera.dll
luxconnector/LuxServer/Camera.pdb
luxconnector/LuxServer/CytoSmart.Logic.CellCounter.dll
luxconnector/LuxServer/CytoSmart.Logic.CellCounter.pdb
luxconnector/LuxServer/CytoSmart.Logic.Lux.dll
luxconnector/LuxServer/CytoSmart.Logic.Lux.pdb
luxconnector/LuxServer/CytoSmart.Logic.Omni.Common.dll
luxconnector/LuxServer/CytoSmart.Logic.Omni.Common.pdb
luxconnector/LuxServer/CytoSmart.Logic.Omni.RobotArm.dll
luxconnector/LuxServer/CytoSmart.Logic.Omni.RobotArm.pdb
luxconnector/LuxServer/CytoSmart.Logic.Omni.dll
luxconnector/LuxServer/CytoSmart.Logic.Omni.pdb
luxconnector/LuxServer/CytoSmart.Services.CellCounter.dll
luxconnector/LuxServer/CytoSmart.Services.CellCounter.pdb
luxconnector/LuxServer/CytoSmart.Services.Common.dll
luxconnector/LuxServer/CytoSmart.Services.Common.pdb
luxconnector/LuxServer/CytoSmart.Services.Lux.dll
luxconnector/LuxServer/CytoSmart.Services.Lux.pdb
luxconnector/LuxServer/CytoSmart.Services.Omni.dll
luxconnector/LuxServer/CytoSmart.Services.Omni.pdb
luxconnector/LuxServer/CytoSmartService.exe
luxconnector/LuxServer/CytoSmartService.exe.config
luxconnector/LuxServer/CytoSmartService.pdb
luxconnector/LuxServer/Device.Core.dll
luxconnector/LuxServer/Device.Core.pdb
luxconnector/LuxServer/Device.dll
luxconnector/LuxServer/Device.pdb
luxconnector/LuxServer/ImageAlgorithms.dll
luxconnector/LuxServer/ImageProcessing.dll
luxconnector/LuxServer/ImageProcessing.pdb
luxconnector/LuxServer/IndexRange.dll
luxconnector/LuxServer/Logging.dll
luxconnector/LuxServer/Logging.pdb
luxconnector/LuxServer/Microsoft.Azure.KeyVault.Core.dll
luxconnector/LuxServer/Microsoft.Azure.Storage.Blob.dll
luxconnector/LuxServer/Microsoft.Azure.Storage.Common.dll
luxconnector-1.1.2.dist-info/LICENSE
luxconnector-1.1.2.dist-info/METADATA
luxconnector-1.1.2.dist-info/WHEEL
luxconnector-1.1.2.dist-info/entry_points.txt
luxconnector-1.1.2.dist-info/top_level.txt
luxconnector-1.1.2.dist-info/RECORD
